Vsvpack.py
Vsvpack-0.0.6.dist-info/LICENSE
Vsvpack-0.0.6.dist-info/METADATA
Vsvpack-0.0.6.dist-info/WHEEL
Vsvpack-0.0.6.dist-info/top_level.txt
Vsvpack-0.0.6.dist-info/RECORD
