Metadata-Version: 2.1
Name: Vsvpack
Version: 0.0.6
Summary: A package for saving and reading simple Data like Setings
Author: PackTheCommand
Author-email: packthecommand@gmail.com
License: UNKNOWN
Platform: UNKNOWN
Classifier: Programming Language :: Python :: 3
Classifier: License :: OSI Approved :: MIT License
Classifier: Operating System :: OS Independent
Requires-Python: >=3.6
License-File: LICENSE
